odoo/addons/stock_dynamic_routing_reserve_rule/README.rst
odoo/addons/stock_dynamic_routing_reserve_rule/__init__.py
odoo/addons/stock_dynamic_routing_reserve_rule/__manifest__.py
odoo/addons/stock_dynamic_routing_reserve_rule/i18n/es_AR.po
odoo/addons/stock_dynamic_routing_reserve_rule/i18n/it.po
odoo/addons/stock_dynamic_routing_reserve_rule/i18n/stock_dynamic_routing_reserve_rule.pot
odoo/addons/stock_dynamic_routing_reserve_rule/models/__init__.py
odoo/addons/stock_dynamic_routing_reserve_rule/models/stock_routing.py
odoo/addons/stock_dynamic_routing_reserve_rule/readme/DESCRIPTION.md
odoo/addons/stock_dynamic_routing_reserve_rule/static/description/icon.png
odoo/addons/stock_dynamic_routing_reserve_rule/static/description/index.html
odoo/addons/stock_dynamic_routing_reserve_rule/templates/stock_routing_templates.xml
odoo/addons/stock_dynamic_routing_reserve_rule/views/stock_routing_views.xml
odoo_addon_stock_dynamic_routing_reserve_rule-18.0.1.0.0.2.dist-info/METADATA
odoo_addon_stock_dynamic_routing_reserve_rule-18.0.1.0.0.2.dist-info/WHEEL
odoo_addon_stock_dynamic_routing_reserve_rule-18.0.1.0.0.2.dist-info/top_level.txt
odoo_addon_stock_dynamic_routing_reserve_rule-18.0.1.0.0.2.dist-info/RECORD
